setup.py
torex/__init__.py
torex/__main__.py
torex/basetorrent.py
torex/exceptions.py
torex.egg-info/PKG-INFO
torex.egg-info/SOURCES.txt
torex.egg-info/dependency_links.txt
torex.egg-info/entry_points.txt
torex.egg-info/requires.txt
torex.egg-info/top_level.txt