Metadata-Version: 1.1
Name: torex
Version: 0.1.1
Summary: Torrent extraction automation
Home-page: https://github.com/adararnon/torex
Author: Adar Arnon
Author-email: adararnon@gmail.com
License: GPL
Download-URL: https://github.com/adararnon/torex/tarball/0.1.1
Keywords: torrent,extraction
Platform: UNKNOWN
